django_react_app/__init__.py
django_react_app/babel.config.json
django_react_app/package-lock.json
django_react_app/package.json
django_react_app/urls.py
django_react_app/views.py
django_react_app/webpack.config.js
django_react_app/src/App.js
django_react_app/src/index.js
django_react_app/src/components/Hello.js
django_react_app/templates/index.html
django_react_app-1.1.0.dist-info/LICENSE
django_react_app-1.1.0.dist-info/METADATA
django_react_app-1.1.0.dist-info/WHEEL
django_react_app-1.1.0.dist-info/top_level.txt
django_react_app-1.1.0.dist-info/RECORD
